odoo/addons/fs_product_brand_multi_image/README.rst
odoo/addons/fs_product_brand_multi_image/__init__.py
odoo/addons/fs_product_brand_multi_image/__manifest__.py
odoo/addons/fs_product_brand_multi_image/i18n/es.po
odoo/addons/fs_product_brand_multi_image/i18n/fs_product_brand_multi_image.pot
odoo/addons/fs_product_brand_multi_image/i18n/it.po
odoo/addons/fs_product_brand_multi_image/models/__init__.py
odoo/addons/fs_product_brand_multi_image/models/fs_product_brand_image.py
odoo/addons/fs_product_brand_multi_image/models/image_tag.py
odoo/addons/fs_product_brand_multi_image/models/product_brand.py
odoo/addons/fs_product_brand_multi_image/readme/CONTRIBUTORS.md
odoo/addons/fs_product_brand_multi_image/readme/DESCRIPTION.md
odoo/addons/fs_product_brand_multi_image/readme/USAGE.md
odoo/addons/fs_product_brand_multi_image/security/fs_product_brand_image.xml
odoo/addons/fs_product_brand_multi_image/static/description/icon.png
odoo/addons/fs_product_brand_multi_image/static/description/index.html
odoo/addons/fs_product_brand_multi_image/views/fs_product_brand_image.xml
odoo/addons/fs_product_brand_multi_image/views/product_brand.xml
odoo_addon_fs_product_brand_multi_image-17.0.1.0.0.3.dist-info/METADATA
odoo_addon_fs_product_brand_multi_image-17.0.1.0.0.3.dist-info/WHEEL
odoo_addon_fs_product_brand_multi_image-17.0.1.0.0.3.dist-info/top_level.txt
odoo_addon_fs_product_brand_multi_image-17.0.1.0.0.3.dist-info/RECORD
